{
  "cache_version": 5,
  "sku": "1102509",
  "assets": [
    {
      "asset_id": "cjsffm85jpxkmfsb2cp7qnjr",
      "asset_name": "BBQ1102509 BBQK Connection Kit - GENESIS 3 Burner",
      "cdn_key": "XBRZ2A26",
      "skus": [
        "1102509"
      ]
    },
    {
      "asset_id": "khrhpkgngktqvmt8cc38jhmf",
      "asset_name": "(cze) BBQK Connection Kit - Genesis 3 burner MasterCopy EMEA",
      "cdn_key": "XBRZ2A26",
      "skus": [
        "1102509"
      ]
    },
    {
      "asset_id": "9xmhkcwsjsr3gx9ckcqpn9kv",
      "asset_name": "(dan) BBQK Connection Kit - Genesis 3 burner MasterCopy EMEA",
      "cdn_key": "XBRZ2A26",
      "skus": [
        "1102509"
      ]
    },
    {
      "asset_id": "skvnmxp766j8spc5pv3493pf",
      "asset_name": "(dut-NL) BBQK Connection Kit - Genesis 3 burner MasterCopy EMEA",
      "cdn_key": "XBRZ2A26",
      "skus": [
        "1102509"
      ]
    },
    {
      "asset_id": "53mtb6h6m76nc2n7qt66mh7",
      "asset_name": "(eng-GB) BBQK Connection Kit - Genesis 3 burner MasterCopy EMEA",
      "cdn_key": "XBRZ2A26",
      "skus": [
        "1102509"
      ]
    },
    {
      "asset_id": "crqf5n8wcr9b24f4nsspc5",
      "asset_name": "(enus) BBQK Connection Kit Spirit 3 burner EMEA",
      "cdn_key": "XBRZ2A26",
      "skus": [
        "1102509"
      ]
    },
    {
      "asset_id": "8mhbs3ht9tvvx7ft8m4cgq4p",
      "asset_name": "(fin) BBQK Connection Kit - Genesis 3 burner MasterCopy EMEA",
      "cdn_key": "XBRZ2A26",
      "skus": [
        "1102509"
      ]
    },
    {
      "asset_id": "3pjvssjvmjn357w8kxzqzqz",
      "asset_name": "(fre-FR) BBQK Connection Kit - Genesis 3 burner MasterCopy EMEA",
      "cdn_key": "XBRZ2A26",
      "skus": [
        "1102509"
      ]
    },
    {
      "asset_id": "5jxntz9k67xrcnmph6s3h75b",
      "asset_name": "(ger-DE) BBQK Connection Kit - Genesis 3 burner MasterCopy EMEA",
      "cdn_key": "XBRZ2A26",
      "skus": [
        "1102509"
      ]
    },
    {
      "asset_id": "xtx3js3f9mgp8sjb68krpzbf",
      "asset_name": "(ita-IT) BBQK Connection Kit - Genesis 3 burner MasterCopy EMEA",
      "cdn_key": "XBRZ2A26",
      "skus": [
        "1102509"
      ]
    },
    {
      "asset_id": "2w4fq9rnk84qnc73n85gqnnf",
      "asset_name": "(no) BBQK Connection Kit - Genesis 3 burner MasterCopy EMEA",
      "cdn_key": "XBRZ2A26",
      "skus": [
        "1102509"
      ]
    },
    {
      "asset_id": "26bg3phkmkgbrpngm5hcgjr",
      "asset_name": "(pol) BBQK Connection Kit - Genesis 3 burner MasterCopy EMEA",
      "cdn_key": "XBRZ2A26",
      "skus": [
        "1102509"
      ]
    },
    {
      "asset_id": "xmr744ckg75pw6qwwkhpbb",
      "asset_name": "(por-PT) BBQK Connection Kit - Genesis 3 burner MasterCopy EMEA",
      "cdn_key": "XBRZ2A26",
      "skus": [
        "1102509"
      ]
    },
    {
      "asset_id": "hhnf6vk3s3qrxzscf6pc733q",
      "asset_name": "(spa-ES) BBQK Connection Kit - Genesis 3 burner MasterCopy EMEA",
      "cdn_key": "XBRZ2A26",
      "skus": [
        "1102509"
      ]
    },
    {
      "asset_id": "js99k3t6s8p4h6vswhhkwh5",
      "asset_name": "(swe-SE) BBQK Connection Kit - Genesis 3 burner MasterCopy EMEA",
      "cdn_key": "XBRZ2A26",
      "skus": [
        "1102509"
      ]
    },
    {
      "asset_id": "jg7sn92k9gc8vr5qc8kt9p95",
      "asset_name": "(enus) BBQK Connection Kit Genesis 3 burner EMEA",
      "cdn_key": "XBRZ2A26",
      "skus": [
        "1102509"
      ]
    }
  ],
  "images": []
}